setup.py
Topsis_Anvi_101903658.egg-info/PKG-INFO
Topsis_Anvi_101903658.egg-info/SOURCES.txt
Topsis_Anvi_101903658.egg-info/dependency_links.txt
Topsis_Anvi_101903658.egg-info/requires.txt
Topsis_Anvi_101903658.egg-info/top_level.txt
topsis/topsis-101903658.py